{"hash":"2cbfaa773c414da5c97e6a0cf2cb9fa9d7db58ae","data":{"metadata":{"siteName":"只是玩玩 | JUST FUN","siteDescription":"Hello"},"post":{"id":"63158312cf533d1c2cf29b30","title":"节气•小雪","content":"<figure class=\"kg-card kg-image-card\"><img src=\"https://cdn.1900.live/2020/11/e78daea837335c8262c0b28c335d9a79.jpg\" class=\"kg-image\" alt loading=\"lazy\" width=\"1728\" height=\"2560\"></figure><p>一夜知冬。</p><p>昨天还是二十好几度，今天就坐跳楼机一样降到了六七度。 </p>","date":"22 November 2020","path":"untitled-4"}},"context":{}}