{"hash":"c29e28eb09cebfa4d5785bfac51829c54a26be66","data":{"metadata":{"siteName":"只是玩玩 | JUST FUN","siteDescription":"Hello"},"post":{"id":"63158312cf533d1c2cf29966","title":"黑房子里的思考[黑历史]","content":"<!--kg-card-begin: markdown--><p>点上一根烟，烟雾缭绕在这个狭小的空间里。电脑里放着昨天找到的一张音乐专辑，没有歌词，只有包含着各种音乐家心声的旋律伴着烟雾升起在这小房间里回荡。<br>\n灯没开，电脑的荧光映在我的脸上，感觉自己有点发呆。每每独自一人时便会有这种无所适从的感觉，没有下一刻、没有明天，总觉得孤身一人，他们都说这是寂寞。</p>\n<p>我起初有点不相信，以为这只是种暂时的现象，现在我相信了——哦，原来这是叫孤独的东西。我试着想脱离这种困境，但心却似陷入泥潭般的月沉越深，陷入了这个黑暗的孤独泥潭的深处。可以思考、可以呼吸但周遭的黑暗让我无法出声，越是愤怒越是无力，有时会伴随着这些东西沉沉睡去，有时却难以入眠，只能听着自己的心跳直到天明。</p>\n<p>总在这个时候期待名为爱情的那个东西，虽活至今日，但却从未体验过那种味道——那是什么味道呢？似未成熟的果子般的涩？还是似良药般的苦？又或是像蜂蜜般的甜？或者说是这些味道加在一起便是爱情的味道？</p>\n<p>——我不得而知，只是心怀几分期待的想尝尝这舌尖上的爱情</p>\n<!--kg-card-end: markdown-->","date":"31 May 2012","path":"hei-fang-zi-li-de-si-kao-hei-li-shi"}},"context":{}}