{"hash":"09771c91682eedafd3ee73b22826856fd274f766","data":{"metadata":{"siteName":"只是玩玩 | JUST FUN","siteDescription":"Hello"},"post":{"id":"63158312cf533d1c2cf29977","title":"其实…","content":"<!--kg-card-begin: markdown--><p>真的寂寞，一个人看了场电影，旁边路人都是几个几个一起看的，我落座后都奇怪的看着我。</p>\n<p>后来一个网友问我为什不和别人一起看？我想了想，好像我没其他认识的好朋友可以一起去看了…昨天为什么哭我忽然想明白了，可能是觉得自己挺失败的吧？来这个城市已经六七年了，却没有一个可以一起看电影的朋友。做人做到这个地步也是忒失败的。</p>\n<p>我不知道是因为家里的原因还是因为其他什么，平时工作比较忙，基本上没有什么时间可以出去跟朋友做交际。每天早上八点到晚上的八点都在工作，周末也要加班，每天神经绷得紧紧的，而且忙来忙去业绩也没有怎么增长，家里长辈还会说教。有些时候真的觉得是挺烦的，总觉得过得很压抑，这也可能也是我喜欢旅游的原因之一吧！毕竟出去之后就可以不用面对这样的环境了，可以无忧无虑做自己想做的事情。</p>\n<p>祝大家圣诞节快乐，可怜一下自己</p>\n<!--kg-card-end: markdown-->","date":"25 December 2016","path":"qi-shi"}},"context":{}}